Metadata-Version: 2.1
Name: pulumi-aws-static-website
Version: 0.4.0
Summary: A Pulumi component to deploy a static website to AWS
Home-page: https://pulumi.com
License: UNKNOWN
Project-URL: Repository, https://github.com/pulumi/pulumi-aws-static-website
Keywords: pulumi aws category/cloud kind/component web
Platform: UNKNOWN
Requires-Python: >=3.7
